{
  "HVIGOR_OHOS_PLUGIN": {
    "MODULES": [
      {
        "MODULE_NAME": "1043bfc77febe75fafec0c4309faccf1",
        "API_TYPE": "stageMode"
      }
    ],
    "NATIVE_COMPILER": "Default",
    "BUILD_MODE": "debug"
  },
  "HVIGOR": {
    "IS_INCREMENTAL": true,
    "IS_DAEMON": true,
    "IS_PARALLEL": true,
    "IS_HVIGORFILE_TYPE_CHECK": false,
    "TASK_TIME": {
      "1043bfc77febe75fafec0c4309faccf1": {
        "CreateModuleInfo": 157791,
        "PreCheckSyscap": 87083,
        "ProcessStartupConfig": 864083,
        "PreviewProcessResource": 272625,
        "PreviewCompileResource": 108088667,
        "PreviewHookCompileResource": 143833,
        "CopyPreviewProfile": 1293833,
        "ReplacePreviewerPage": 590042,
        "buildPreviewerResource": 77083,
        "PreviewUpdateAssets": 579167,
        "PreviewArkTS": 4149297917,
        "PreviewBuild": 143042
      }
    },
    "APIS": [
      "getHvigorConfig",
      "getRootNodeDescriptor",
      "getChildNode",
      "getNodeByName",
      "getAllNodes",
      "getRootNode",
      "getNodeName",
      "getNodePath",
      "subNodes",
      "getExtraOption",
      "getExtParam",
      "getExtParams",
      "getProperty",
      "getProperties",
      "getParameter",
      "getProductName",
      "nodesEvaluated",
      "getCommandEntryTask",
      "getStartParams"
    ],
    "CONFIG_PROPERTIES": {},
    "TOTAL_TIME": 4359873708,
    "BUILD_ID": "202603142217473390"
  }
}